yandex_delivery/__init__.py
yandex_delivery/api.py
yandex_delivery/exceptions.py
yandex_delivery-0.0.1.dist-info/DESCRIPTION.rst
yandex_delivery-0.0.1.dist-info/METADATA
yandex_delivery-0.0.1.dist-info/RECORD
yandex_delivery-0.0.1.dist-info/WHEEL
yandex_delivery-0.0.1.dist-info/metadata.json
yandex_delivery-0.0.1.dist-info/top_level.txt
