Metadata-Version: 2.0
Name: yandex-delivery
Version: 0.0.1
Summary: Yandex Delivery python client (python-клиент «Яндекс.Доставик»
Home-page: https://github.com/daniilr/yandex-delivery-pythonlj
Author: Daniil Ryzhkov
Author-email: i@daniil-r.ru
License: MIT License
Download-URL: https://github.com/daniilr/yandex-delivery-python/
Keywords: yandex,delivery,logistics,business
Platform: osx
Platform: posix
Platform: linux
Platform: windows
Classifier: Programming Language :: Python :: 3.4
Classifier: Programming Language :: Python :: 3.5
Classifier: Intended Audience :: Developers
Classifier: License :: OSI Approved :: MIT License
Classifier: Development Status :: 3 - Alpha
Requires-Dist: requests (>=2.10.0)
